[
  {
    "key": "ctrl+h",
    "command": "workbench.action.navigateLeft",
    "when": "vim.mode == 'Normal'"
  },
  {
    "key": "ctrl+l",
    "command": "workbench.action.navigateRight",
    "when": "vim.mode == 'Normal'"
  },
  {
    "key": "ctrl+j",
    "command": "workbench.action.navigateDown",
    "when": "vim.mode == 'Normal'"
  },
  {
    "key": "ctrl+k",
    "command": "workbench.action.navigateUp",
    "when": "vim.mode == 'Normal'"
  },
  {
    "key": "ctrl+shift+tab",
    "command": "workbench.action.previousEditor",
    "when": "!activeEditorGroupEmpty"
  },
  {
    "key": "ctrl+tab",
    "command": "workbench.action.nextEditor",
    "when": "!activeEditorGroupEmpty"
  },
  {
    "key": "ctrl+a m",
    "command": "workbench.action.toggleMaximizedPanel",
    "when": "terminalFocus"
  }
]
